{"label": "jeuxvideos", "transcript": [{"text": "au programme du d\u00e9 de ce vendredi 2 ao\u00fbt", "start": 0.04, "duration": 4.04}, {"text": "on d\u00e9marre avec les r\u00e9sultats financiers", "start": 2.399, "duration": 4.36}, {"text": "d' on encha\u00eene avec Deadpool qui rend", "start": 4.08, "duration": 4.88}, {"text": "les joueurs fous et on terminera sur le", "start": 6.759, "duration": 5.681}, {"text": "retour de Squid game le D c'est", "start": 8.96, "duration": 6.24}, {"text": "parti electronic Arts a fait le point", "start": 12.44, "duration": 4.96}, {"text": "sur ses r\u00e9sultats financiers l'\u00e9diteur a", "start": 15.2, "duration": 4.76}, {"text": "g\u00e9n\u00e9r\u00e9 un b\u00e9n\u00e9fice de 280 millions de", "start": 17.4, "duration": 4.32}, {"text": "dollars au cours du premier trimestre de", "start": 19.96, "duration": 4.639}, {"text": "son exercice fiscal 2024 un chiffre en", "start": 21.72, "duration": 4.879}, {"text": "baisse de 30 % par rapport \u00e0 l'ann\u00e9e", "start": 24.599, "duration": 3.52}, {"text": "pr\u00e9c\u00e9dente c'est clairement une chute", "start": 26.599, "duration": 3.401}, {"text": "consid\u00e9rable par rapport au b\u00e9n\u00e9fice de", "start": 28.119, "duration": 4.241}, {"text": "402 millions de dollars enregistr\u00e9s au", "start": 30.0, "duration": 5.079}, {"text": "premier trimestre 2023 au cours des 3", "start": 32.36, "duration": 5.199}, {"text": "mois pr\u00e9c\u00e9dents le 20 juin 2024 EA a", "start": 35.079, "duration": 4.921}, {"text": "g\u00e9n\u00e9r\u00e9 un chiffre d'affaires de 1,66", "start": 37.559, "duration": 4.201}, {"text": "milliards de dollars soit une baisse de", "start": 40.0, "duration": 4.28}, {"text": "13 % en glissement annuel avec des", "start": 41.76, "duration": 5.119}, {"text": "r\u00e9servations nettes en baisse de 20 % \u00e0", "start": 44.28, "duration": 5.32}, {"text": "1,6 milliard de dollars apr\u00e8s tout il", "start": 46.879, "duration": 4.761}, {"text": "fallait pas s'attendre \u00e0 grand-chose i", "start": 49.6, "duration": 5.4}, {"text": "n'a lanc\u00e9 que eSports F1 24 et Tales of", "start": 51.64, "duration": 6.239}, {"text": "zenzara zoo au cours de la p\u00e9riode il", "start": 55.0, "duration": 4.519}, {"text": "n'avait donc que deux nouveaux titres", "start": 57.879, "duration": 3.2}, {"text": "sur les elle s'appuyait pour augmenter", "start": 59.519, "duration": 3.121}, {"text": "les ventes de jeux complets par contre", "start": 61.079, "duration": 3.4}, {"text": "l'\u00e9diteur ressort quand m\u00eame gagnant les", "start": 62.64, "duration": 3.519}, {"text": "pr\u00e9visions pour le trimestre tablaient", "start": 64.479, "duration": 3.521}, {"text": "sur une fourchette haute de 1,5", "start": 66.159, "duration": 3.28}, {"text": "milliards de dollars de r\u00e9servation", "start": 68.0, "duration": 3.24}, {"text": "nette de sorte que malgr\u00e9 cette baisse", "start": 69.439, "duration": 3.961}, {"text": "de 20 % d'une ann\u00e9e \u00e0 l'autre EA a", "start": 71.24, "duration": 4.239}, {"text": "r\u00e9ussi \u00e0 d\u00e9passer les attentes le bilan", "start": 73.4, "duration": 4.2}, {"text": "a en tout cas l'air de rendre le PDG dia", "start": 75.479, "duration": 4.121}, {"text": "Andrew Wilson plut\u00f4t content il a", "start": 77.6, "duration": 4.28}, {"text": "qualifi\u00e9 le premier trimestre 2024", "start": 79.6, "duration": 4.44}, {"text": "d'incroyable pour l'entreprise en fait", "start": 81.88, "duration": 3.72}, {"text": "les r\u00e9sultats ont carr\u00e9ment d\u00e9pass\u00e9 les", "start": 84.04, "duration": 3.8}, {"text": "attentes surtout parce que EA Sport FC", "start": 85.6, "duration": 4.68}, {"text": "mobile a enregistr\u00e9 un nombre rec cor de", "start": 87.84, "duration": 4.639}, {"text": "r\u00e9servation nette d'autres titres se", "start": 90.28, "duration": 4.519}, {"text": "sont surpass\u00e9s comme FC online et FC", "start": 92.479, "duration": 4.96}, {"text": "mobile Madden nfl24 apr\u00e8s ce sont quand", "start": 94.799, "duration": 4.561}, {"text": "m\u00eame les consoes et les PC qui restent", "start": 97.439, "duration": 3.64}, {"text": "les plus performants pour l'entreprise", "start": 99.36, "duration": 3.24}, {"text": "les ventes de consoles contribuant \u00e0", "start": 101.079, "duration": 3.801}, {"text": "hauteur d'un milliard de dollars les PC", "start": 102.6, "duration": 4.44}, {"text": "\u00e0 hauteur de 365 millions de dollars et", "start": 104.88, "duration": 4.199}, {"text": "les mobiles en 3e position \u00e0 hauteur de", "start": 107.04, "duration": 4.439}, {"text": "290 millions de dollars le sport", "start": 109.079, "duration": 3.481}, {"text": "continuera de ramener toujours plus", "start": 111.479, "duration": 3.721}, {"text": "d'argent \u00e0 EA on rappelle que eSports FC", "start": 112.56, "duration": 5.0}, {"text": "25 proposera un passe saisonnier payant", "start": 115.2, "duration": 3.959}, {"text": "qui offrira des r\u00e9compenses dans trois", "start": 117.56, "duration": 3.879}, {"text": "modes de jeu populaire Ultimate Team", "start": 119.159, "duration": 4.521}, {"text": "carri\u00e8re et club pro \u00e7a sera disponible", "start": 121.439, "duration": 4.161}, {"text": "en parall\u00e8le du passe de saison qui est", "start": 123.68, "duration": 3.56}, {"text": "lui compl\u00e8tement gratuit reste \u00e0 voir", "start": 125.6, "duration": 3.159}, {"text": "comment \u00e7a sera per\u00e7u de la part des", "start": 127.24, "duration": 3.2}, {"text": "joueurs en attendant on vous invite \u00e0", "start": 128.759, "duration": 3.601}, {"text": "lire notre preview du jeu disponible sur", "start": 130.44, "duration": 4.4}, {"text": "le site avant de passer \u00e0 la suite bonne", "start": 132.36, "duration": 3.76}, {"text": "nouvelle pour les amateurs de jeux", "start": 134.84, "duration": 2.96}, {"text": "Pok\u00e9mon le tout premier jeu Donjon", "start": 136.12, "duration": 3.56}, {"text": "Myst\u00e8re arrive sur le service en ligne", "start": 137.8, "duration": 3.719}, {"text": "de la Nintendo switch Pok\u00e9mon Donjon", "start": 139.68, "duration": 3.68}, {"text": "Myst\u00e8re red Rescue Team arrivera dans la", "start": 141.519, "duration": 4.201}, {"text": "biblioth\u00e8que GBA dispo pour les membres", "start": 143.36, "duration": 5.2}, {"text": "de l'expansion pack le 9 ao\u00fbt l'histoire", "start": 145.72, "duration": 4.28}, {"text": "elle tourne autour du joueur un", "start": 148.56, "duration": 3.039}, {"text": "personnage humain qui a \u00e9t\u00e9 transform\u00e9", "start": 150.0, "duration": 3.92}, {"text": "en Pok\u00e9mon et qui est amn\u00e9sique il va", "start": 151.599, "duration": 3.801}, {"text": "devoir s'allier avec une \u00e9quipe de", "start": 153.92, "duration": 3.959}, {"text": "sauvetage compos\u00e9 d'autres Pok\u00e9mon pour", "start": 155.4, "duration": 3.839}, {"text": "effectuer des missions afin d'aider les", "start": 157.879, "duration": 3.0}, {"text": "autres et tenter de d\u00e9couvrir leur", "start": 159.239, "duration": 3.321}, {"text": "v\u00e9ritable identit\u00e9 d'ailleurs le jeu a", "start": 160.879, "duration": 3.321}, {"text": "eu le droit \u00e0 un remake sur switch sous", "start": 162.56, "duration": 3.84}, {"text": "le nom de Pok\u00e9mon mystery Dungeon Rescue", "start": 164.2, "duration": 4.56}, {"text": "Team DX sorti en 2020 mais \u00e7a fait du", "start": 166.4, "duration": 3.759}, {"text": "bien de le retrouver dans sa version", "start": 168.76, "duration": 3.8}, {"text": "d'origine \u00e7a sera le 21e jeu Game Boy", "start": 170.159, "duration": 4.041}, {"text": "Advance \u00e0 \u00eatre ajout\u00e9 au service", "start": 172.56, "duration": 3.84}, {"text": "Nintendo switch online allez on passe \u00e0", "start": 174.2, "duration": 4.28}, {"text": "la suite le nouveau film Deadpool et", "start": 176.4, "duration": 3.88}, {"text": "Wolverine est sorti au cin\u00e9ma CMA les", "start": 178.48, "duration": 3.24}, {"text": "deux personnages l\u00e9gendaires s'unissent", "start": 180.28, "duration": 3.48}, {"text": "ici pour le meilleur et pour le pire", "start": 181.72, "duration": 3.64}, {"text": "l'occasion de reformer une fois de plus", "start": 183.76, "duration": 3.88}, {"text": "le duo de star Ryan Reynolds Yuk Jackman", "start": 185.36, "duration": 4.12}, {"text": "alors que ce dernier s'est enfin d\u00e9cid\u00e9", "start": 187.64, "duration": 3.679}, {"text": "\u00e0 renfiler le costume du personnage qu'", "start": 189.48, "duration": 3.44}, {"text": "l'a rendu c\u00e9l\u00e8bre avec cette sortie", "start": 191.319, "duration": 3.321}, {"text": "Disney frappe tr\u00e8s fort Deadpool et", "start": 192.92, "duration": 3.48}, {"text": "Wolverine a \u00e9t\u00e9 tr\u00e8s bien re\u00e7u par la", "start": 194.64, "duration": 3.4}, {"text": "presse et le public et conna\u00eet aussi un", "start": 196.4, "duration": 3.479}, {"text": "succ\u00e8s retentissant au box office le", "start": 198.04, "duration": 4.04}, {"text": "film a engrang\u00e9 pr\u00e8s de 600 millions de", "start": 199.879, "duration": 3.92}, {"text": "dollars et devrait logiquement devenir", "start": 202.08, "duration": 3.799}, {"text": "le film all rated le plus rentable de", "start": 203.799, "duration": 3.601}, {"text": "l'histoire du cin\u00e9ma et pendant que", "start": 205.879, "duration": 3.92}, {"text": "Marvel se fait un maximum d'argent avec", "start": 207.4, "duration": 4.08}, {"text": "les entr\u00e9es en salle d'autres personnes", "start": 209.799, "duration": 3.36}, {"text": "moins bien intentionn\u00e9es sur Internet", "start": 211.48, "duration": 3.16}, {"text": "essayent aussi d'exploiter le filon si", "start": 213.159, "duration": 3.0}, {"text": "vous jetez un coup d'\u0153il sur ebay par", "start": 214.64, "duration": 3.56}, {"text": "exemple vous remarquerez peut-\u00eatre que", "start": 216.159, "duration": 4.0}, {"text": "quelqu'un essaie de vendre une copie \u00e0", "start": 218.2, "duration": 4.92}, {"text": "970 dollars de ce jeu Deadpool datant de", "start": 220.159, "duration": 5.401}, {"text": "2013 et si jamais vous \u00eates tent\u00e9 piti\u00e9", "start": 223.12, "duration": 4.399}, {"text": "ne craquez pas m\u00eame si ce jeu d\u00e9velopp\u00e9", "start": 225.56, "duration": 4.28}, {"text": "par Activision est d\u00e9sormais une dor\u00e9", "start": 227.519, "duration": 3.8}, {"text": "rare Deadpool le jeu est sorti \u00e0", "start": 229.84, "duration": 5.08}, {"text": "l'origine en 2013 sur Xbox 360 PS3 et PC", "start": 231.319, "duration": 5.441}, {"text": "c'\u00e9tait un titre d'action plut\u00f4t ok chez", "start": 234.92, "duration": 4.039}, {"text": "nous il a h\u00e9rit\u00e9 de la note de 13/ 20", "start": 236.76, "duration": 3.92}, {"text": "c'est assez fid\u00e8le \u00e0 l'univers on y", "start": 238.959, "duration": 3.521}, {"text": "retrouve de l'humour bien potach et des", "start": 240.68, "duration": 3.639}, {"text": "r\u00e9f\u00e9rences \u00e0 gogo en plus en version", "start": 242.48, "duration": 3.959}, {"text": "anglaise Deadpool est incarn\u00e9 par Nolan", "start": 244.319, "duration": 4.041}, {"text": "North l'acteur de Nathan Drake par", "start": 246.439, "duration": 3.601}, {"text": "contre on retrouvait aussi pas mal de", "start": 248.36, "duration": 3.799}, {"text": "bugs c'\u00e9tait r\u00e9p\u00e9titif \u00e0 l'extr\u00eame et le", "start": 250.04, "duration": 4.24}, {"text": "gameplay \u00e9tait quand m\u00eame sans saveur", "start": 252.159, "duration": 4.2}, {"text": "bref rien qui ne vaut 900 dollars le", "start": 254.28, "duration": 3.679}, {"text": "truc c'est que le jeu a \u00e9t\u00e9 retir\u00e9 des", "start": 256.359, "duration": 3.88}, {"text": "stor en 2017 apr\u00e8s l'expiration de la", "start": 257.959, "duration": 4.281}, {"text": "licence Marvel d'Activision du coup le", "start": 260.239, "duration": 3.721}, {"text": "seul moyen l\u00e9gal de jouer \u00e0 Deadpool si", "start": 262.24, "duration": 3.399}, {"text": "vous ne le poss\u00e9dez pas d\u00e9j\u00e0 c'est de", "start": 263.96, "duration": 3.44}, {"text": "trouver une copie physique et forc\u00e9ment", "start": 265.639, "duration": 3.56}, {"text": "\u00e7a se fait rare \u00e0 part sur ebay o\u00f9 vous", "start": 267.4, "duration": 3.48}, {"text": "avez beaup beaucoup d'options tr\u00e8s", "start": 269.199, "duration": 3.44}, {"text": "co\u00fbteuses une recherche rapide sur le", "start": 270.88, "duration": 3.68}, {"text": "site d'ench\u00e8re r\u00e9v\u00e8le des dizaines et", "start": 272.639, "duration": 3.441}, {"text": "des dizaines de copies de Deadpool sur", "start": 274.56, "duration": 2.84}, {"text": "toutes les plateformes il y a quand m\u00eame", "start": 276.08, "duration": 3.119}, {"text": "quelques personnees honn\u00eate dans le Lot", "start": 277.4, "duration": 3.32}, {"text": "certains exemplaires d'occasion sont", "start": 279.199, "duration": 3.161}, {"text": "vendus \u00e0 des prix tr\u00e8s corrects de", "start": 280.72, "duration": 4.08}, {"text": "l'ordre de 40 \u00e0 70 dollars pourtant une", "start": 282.36, "duration": 4.76}, {"text": "autre personne en demande plus de 2000", "start": 284.8, "duration": 5.08}, {"text": "dollars combien et sur la m\u00eame boutique", "start": 287.12, "duration": 4.76}, {"text": "mais c\u00f4t\u00e9 France je suis tomb\u00e9 sur une", "start": 289.88, "duration": 5.68}, {"text": "annonce \u00e0 2300 \u20ac c'est juste ahurissant", "start": 291.88, "duration": 5.319}, {"text": "bref faites bien vos recherches avant de", "start": 295.56, "duration": 4.16}, {"text": "passer \u00e0 la caisse avant de passer au", "start": 297.199, "duration": 3.961}, {"text": "dernier sujet on vous partage cette", "start": 299.72, "duration": 3.479}, {"text": "rumeur qui anfle si de nombreux jeux", "start": 301.16, "duration": 3.72}, {"text": "Xbox sont pr\u00e9vus au cours des mois", "start": 303.199, "duration": 3.361}, {"text": "prochains il semblerait que l'un d'entre", "start": 304.88, "duration": 3.599}, {"text": "eux soit repouss\u00e9 \u00e0 l'ann\u00e9e prochaine et", "start": 306.56, "duration": 3.56}, {"text": "oui selon Tom Warren de theeverge", "start": 308.479, "duration": 4.0}, {"text": "Microsoft et Obsidian Entertainment", "start": 310.12, "duration": 4.48}, {"text": "s'appr\u00eatent \u00e0 annoncer que voud a \u00e9t\u00e9", "start": 312.479, "duration": 4.401}, {"text": "retard\u00e9 jusqu'au d\u00e9but de l'ann\u00e9e 2025", "start": 314.6, "duration": 3.96}, {"text": "pour l'instant le RPG est officiellement", "start": 316.88, "duration": 3.12}, {"text": "pr\u00e9vu pour l'automne mais \u00e7a pourrait", "start": 318.56, "duration": 3.68}, {"text": "changer selon Warren Microsoft cherche \u00e0", "start": 320.0, "duration": 3.84}, {"text": "lib\u00e9rer de l'espace dans son calendrier", "start": 322.24, "duration": 3.72}, {"text": "de sortie surtout parce que la sortie de", "start": 323.84, "duration": 4.359}, {"text": "STALKER 2 a \u00e9t\u00e9 repouss\u00e9e \u00e0 novembre ne", "start": 325.96, "duration": 3.4}, {"text": "vous inqui\u00e9tez pas", "start": 328.199, "duration": 3.241}, {"text": "serait dans un tr\u00e8s bon \u00e9tat le retard", "start": 329.36, "duration": 3.72}, {"text": "aurait juste pour but de donner un peu", "start": 331.44, "duration": 3.44}, {"text": "d'air \u00e0 toutes les grandes exclusivit\u00e9s", "start": 333.08, "duration": 4.239}, {"text": "Xbox \u00e0 venir c'est le retour de la s\u00e9rie", "start": 334.88, "duration": 4.2}, {"text": "cor\u00e9enne qui a le plus cartonn\u00e9 sur", "start": 337.319, "duration": 3.88}, {"text": "Netflix et c'est bien gr\u00e2ce \u00e0 elle que", "start": 339.08, "duration": 4.399}, {"text": "vous mangez des k drama \u00e0 foison depuis", "start": 341.199, "duration": 3.641}, {"text": "quelques ann\u00e9es on veut bien s\u00fbr parler", "start": 343.479, "duration": 3.481}, {"text": "de Squid game la s\u00e9rie qui a rapport\u00e9", "start": 344.84, "duration": 4.88}, {"text": "aux alentours de 900 millions de dollars", "start": 346.96, "duration": 5.32}, {"text": "\u00e0 Netflix le cr\u00e9ateur de la s\u00e9rie Wang", "start": 349.72, "duration": 5.0}, {"text": "Dong Yuk a r\u00e9cemment confirm\u00e9 via un", "start": 352.28, "duration": 4.28}, {"text": "teaser que la nouvelle saison de Squid", "start": 354.72, "duration": 4.319}, {"text": "game sera diffus\u00e9e sur Netflix le 26", "start": 356.56, "duration": 3.919}, {"text": "d\u00e9cembre prochain alors \u00e0 quoi", "start": 359.039, "duration": 3.201}, {"text": "s'attendre pour la suite le synopsis", "start": 360.479, "duration": 3.921}, {"text": "officiel de la saison 2 r\u00e9v\u00e8le que 3 ans", "start": 362.24, "duration": 5.799}, {"text": "apr\u00e8s sa victoire le joueur 456 Guy un", "start": 364.4, "duration": 5.76}, {"text": "serait d\u00e9termin\u00e9 \u00e0 mettre fin au jeux", "start": 368.039, "duration": 4.041}, {"text": "mortel il va d'ailleurs utiliser sa", "start": 370.16, "duration": 3.92}, {"text": "fortune pour financer sa qu\u00eate il va", "start": 372.08, "duration": 3.28}, {"text": "commencer \u00e0 rechercher l'homme en", "start": 374.08, "duration": 3.04}, {"text": "costume qui jouit au dagj dans le m\u00e9tro", "start": 375.36, "duration": 3.32}, {"text": "pour ceux qui se souviennent c'est le", "start": 377.12, "duration": 3.4}, {"text": "premier contact des participants avec", "start": 378.68, "duration": 3.959}, {"text": "les jeux \u00e9videmment sa mission se r\u00e9v\u00e8le", "start": 380.52, "duration": 4.2}, {"text": "plus dangereuse que pr\u00e9vu pour d\u00e9truire", "start": 382.639, "duration": 4.481}, {"text": "l'organisation il doit r\u00e9int\u00e9grer le jeu", "start": 384.72, "duration": 3.8}, {"text": "cette nouvelle saison promet d'\u00eatre", "start": 387.12, "duration": 3.12}, {"text": "encore plus intense AC avec des enjeux", "start": 388.52, "duration": 3.44}, {"text": "encore plus \u00e9lev\u00e9s on va pouvoir", "start": 390.24, "duration": 3.239}, {"text": "d\u00e9couvrir de nouveaux visages et", "start": 391.96, "duration": 3.12}, {"text": "peut-\u00eatre le possible retour de", "start": 393.479, "duration": 3.041}, {"text": "personnages dont le sort restait", "start": 395.08, "duration": 3.08}, {"text": "incertain \u00e0 la fin de la premi\u00e8re saison", "start": 396.52, "duration": 2.88}, {"text": "cette annonce s'accompagne de la", "start": 398.16, "duration": 2.879}, {"text": "nouvelle surprenante que le show a", "start": 399.4, "duration": 4.079}, {"text": "\u00e9galement \u00e9t\u00e9 renouvel\u00e9 pour une 3\u00e8 et", "start": 401.039, "duration": 5.241}, {"text": "ultime saison pr\u00e9vue pour 2025 l'attente", "start": 403.479, "duration": 4.801}, {"text": "autour de cette 3\u00e8me saison est immense", "start": 406.28, "duration": 3.639}, {"text": "d'autant plus que peu de d\u00e9tails ont \u00e9t\u00e9", "start": 408.28, "duration": 3.319}, {"text": "r\u00e9v\u00e9l\u00e9s les spectateurs semblent ravis", "start": 409.919, "duration": 3.481}, {"text": "d'apprendre que la s\u00e9rie ne s'\u00e9ternisera", "start": 411.599, "duration": 3.361}, {"text": "pas sur plusieurs ann\u00e9es comme d'autres", "start": 413.4, "duration": 3.68}, {"text": "show qui perdent de leur valeur et de la", "start": 414.96, "duration": 3.679}, {"text": "qualit\u00e9 au fur et \u00e0 mesure de toute", "start": 417.08, "duration": 3.28}, {"text": "fa\u00e7on il y a toujours d'autres mani\u00e8res", "start": 418.639, "duration": 3.68}, {"text": "d'exploiter l'univers de la franchise et", "start": 420.36, "duration": 3.88}, {"text": "\u00e7a Netflix l'a bien compris l'ann\u00e9e", "start": 422.319, "duration": 3.44}, {"text": "derni\u00e8re la plateforme a lanc\u00e9 une", "start": 424.24, "duration": 3.799}, {"text": "\u00e9mission de t\u00e9l\u00e9r\u00e9alit\u00e9 bas\u00e9e sur squid", "start": 425.759, "duration": 3.921}, {"text": "game d'ailleurs \u00e7a s'est pas bien pass\u00e9", "start": 428.039, "duration": 3.681}, {"text": "du tout he il y a eu plein de scandales", "start": 429.68, "duration": 3.72}, {"text": "bref plus tard dans l'ann\u00e9e Netflix", "start": 431.72, "duration": 3.44}, {"text": "pr\u00e9voit \u00e9galement de lancer un jeu", "start": 433.4, "duration": 3.639}, {"text": "multijoueur squid game encore mieux", "start": 435.16, "duration": 4.24}, {"text": "selon Jeff snyider David Fincher le", "start": 437.039, "duration": 4.56}, {"text": "r\u00e9alisateur de Seven et The Killer", "start": 439.4, "duration": 4.239}, {"text": "travaillerait discr\u00e8tement sur le projet", "start": 441.599, "duration": 4.121}, {"text": "d'un remake am\u00e9ricain pour squid game", "start": 443.639, "duration": 3.921}, {"text": "m\u00eame si nous ne savons rien pour l'heure", "start": 445.72, "duration": 3.44}, {"text": "de ce remake il semblerait que la", "start": 447.56, "duration": 3.44}, {"text": "direction tion entreprise par Fincher", "start": 449.16, "duration": 4.319}, {"text": "sur ce squid game US soit encore plus", "start": 451.0, "duration": 4.199}, {"text": "d\u00e9rangeante si on repense \u00e0 une \u0153uvre", "start": 453.479, "duration": 4.12}, {"text": "comme seven on peut en effet imaginer", "start": 455.199, "duration": 4.56}, {"text": "une s\u00e9rie o\u00f9 la psychologie sera au c\u0153ur", "start": 457.599, "duration": 4.241}, {"text": "de l'intrigue bref vous n'avez pas fini", "start": 459.759, "duration": 3.961}, {"text": "de manger du squid game le D\u00e9lice est", "start": 461.84, "duration": 3.24}, {"text": "fini place au sondage hier on vous", "start": 463.72, "duration": 2.879}, {"text": "demandait si vous pensez que les Souls", "start": 465.08, "duration": 3.48}, {"text": "light comme Elden ring devrai \u00e0 l'avenir", "start": 466.599, "duration": 3.04}, {"text": "avoir davantage d'options", "start": 468.56, "duration": 3.28}, {"text": "d'accessibilit\u00e9 comme une fonction pause", "start": 469.639, "duration": 4.28}, {"text": "par exemple 44 % disent non c'est tr\u00e8s", "start": 471.84, "duration": 4.56}, {"text": "bien comme \u00e7a 37 % sont pour ils disent", "start": 473.919, "duration": 4.68}, {"text": "que \u00e7a manque d'accessibilit\u00e9 et 20 %", "start": 476.4, "duration": 4.04}, {"text": "non' juste pas d'avis voici notre", "start": 478.599, "duration": 3.481}, {"text": "question du jour comptez-vous regarder", "start": 480.44, "duration": 3.56}, {"text": "squid game saison 2 le sondage est \u00e0", "start": 482.08, "duration": 3.399}, {"text": "retrouver directement dans l'onglet", "start": 484.0, "duration": 3.479}, {"text": "communaut\u00e9 de notre cha\u00eene YouTube ce", "start": 485.479, "duration": 3.521}, {"text": "coup si le d\u00e9li c'est bel et bien fini", "start": 487.479, "duration": 5.881}, {"text": "rendez-vous lundi pour la suite Ciao", "start": 489.0, "duration": 4.36}]}