{"label": "education", "transcript": [{"text": "[Musique]", "start": 0.84, "duration": 8.119}, {"text": "de quoi est constitu\u00e9 le soleil et d'o\u00f9", "start": 16.119, "duration": 4.481}, {"text": "vient sa chaleur VI", "start": 18.16, "duration": 6.279}, {"text": "ison VI alt easy quelle est la taille du", "start": 20.6, "duration": 5.64}, {"text": "soleil est-ce que c'est une grosse", "start": 24.439, "duration": 3.321}, {"text": "\u00e9toile par rapport \u00e0", "start": 26.24, "duration": 4.32}, {"text": "d'autres que tu sois \u00e0 Paris ou Sydney", "start": 27.76, "duration": 4.44}, {"text": "tu verras toujours le soleil briller", "start": 30.56, "duration": 3.44}, {"text": "c'est l'\u00e9toile la plus proche de notre", "start": 32.2, "duration": 4.6}, {"text": "Terre le soleil est n\u00e9 il y a 4,5", "start": 34.0, "duration": 4.719}, {"text": "milliards d'ann\u00e9es quand un immense", "start": 36.8, "duration": 3.68}, {"text": "nuage de poussi\u00e8re et de gaz s'est", "start": 38.719, "duration": 3.961}, {"text": "effondr\u00e9 dans la Voie Lact\u00e9e il est au", "start": 40.48, "duration": 4.16}, {"text": "centre de notre syst\u00e8me plan\u00e9taire qui", "start": 42.68, "duration": 4.719}, {"text": "s'appelle le syst\u00e8me solaire et dans ce", "start": 44.64, "duration": 5.28}, {"text": "syst\u00e8me il est la seule \u00e9toile immense", "start": 47.399, "duration": 5.441}, {"text": "110 fois la taille de la Terre il y", "start": 49.92, "duration": 5.479}, {"text": "aurait 400 milliards d'Autres soleil", "start": 52.84, "duration": 4.519}, {"text": "dans notre galaxie des \u00e9toiles plus", "start": 55.399, "duration": 4.281}, {"text": "grandes encore et d'autres plus petites", "start": 57.359, "duration": 4.84}, {"text": "regarde il est l\u00e0 notre Soleil au niveau", "start": 59.68, "duration": 5.6}, {"text": "de cette fl\u00e8che le soleil est une \u00e9norme", "start": 62.199, "duration": 6.721}, {"text": "boule de gaz compos\u00e9 \u00e0 73 % d'hydrog\u00e8ne", "start": 65.28, "duration": 6.76}, {"text": "25% d'h\u00e9lium et environ 2 % d'autes gaz", "start": 68.92, "duration": 5.48}, {"text": "et de m\u00e9tau dans son noyau des millions", "start": 72.04, "duration": 4.2}, {"text": "de tonnes d'hydrog\u00e8ne sont transform\u00e9 en", "start": 74.4, "duration": 4.039}, {"text": "h\u00e9lium c'est un peu son carburant et", "start": 76.24, "duration": 5.12}, {"text": "c'est ce qui produit sa chaleur 5500 de", "start": 78.439, "duration": 5.081}, {"text": "en sa surface et jusqu'\u00e0 15 millions en", "start": 81.36, "duration": 4.28}, {"text": "son", "start": 83.52, "duration": 2.12}, {"text": "c\u0153ur od pourquoi le soleil est-il", "start": 88.92, "duration": 5.879}, {"text": "important pour les plantes la lumi\u00e8re du", "start": 92.439, "duration": 4.081}, {"text": "soleil et ses rayons aussi sont", "start": 94.799, "duration": 3.68}, {"text": "essentiels \u00e0 la vie chez les \u00eatres", "start": 96.52, "duration": 3.599}, {"text": "humains cette lumi\u00e8re permet de", "start": 98.479, "duration": 3.841}, {"text": "fabriquer la vitamine D une vitamine qui", "start": 100.119, "duration": 4.561}, {"text": "t'aide \u00e0 bien grandir la lumi\u00e8re est", "start": 102.32, "duration": 4.479}, {"text": "aussi bonne pour le moral elle agit sur", "start": 104.68, "duration": 4.479}, {"text": "la fabrication de la dopamine l'hormone", "start": 106.799, "duration": 4.121}, {"text": "du bonheur non on ne pourrait pas se", "start": 109.159, "duration": 3.841}, {"text": "passer du soleil sans Lui notre terre ne", "start": 110.92, "duration": 3.839}, {"text": "serait qu'une plan\u00e8te sombre et froide", "start": 113.0, "duration": 3.84}, {"text": "vraiment tr\u00e8s froide il ferait moin", "start": 114.759, "duration": 5.201}, {"text": "270\u00b0gr il n'y aurait plus aucune vie c", "start": 116.84, "duration": 5.52}, {"text": "lumi\u00e8re est une \u00e9nergie vitale les", "start": 119.96, "duration": 3.92}, {"text": "plantes par exemple ne pourraient plus", "start": 122.36, "duration": 3.48}, {"text": "pousser oui parce que c'est la lumi\u00e8re", "start": 123.88, "duration": 4.0}, {"text": "du soleil qui permet aux plantes de se", "start": 125.84, "duration": 3.839}, {"text": "nourrir et de se d\u00e9velopper c'est ce", "start": 127.88, "duration": 3.64}, {"text": "qu'on appelle la", "start": 129.679, "duration": 4.001}, {"text": "photosynth\u00e8se quels sont les dangers du", "start": 131.52, "duration": 6.6}, {"text": "soleil vior her Planet hit record", "start": 133.68, "duration": 6.44}, {"text": "qu'est-ce qu'un coup de soleil comment", "start": 138.12, "duration": 3.16}, {"text": "se", "start": 140.12, "duration": 3.24}, {"text": "forme-t-il le soleil est bon pour la", "start": 141.28, "duration": 4.239}, {"text": "plan\u00e8te mais l'activit\u00e9 humaine la", "start": 143.36, "duration": 4.72}, {"text": "pollution la d\u00e9forestation d\u00e9truit petit", "start": 145.519, "duration": 4.641}, {"text": "\u00e0 petit tout ce qui prot\u00e8ge la Terre des", "start": 148.08, "duration": 3.92}, {"text": "rayons nocifs du soleil et de son", "start": 150.16, "duration": 3.96}, {"text": "extr\u00eame chaleur c'est pour \u00e7a qu'il fait", "start": 152.0, "duration": 3.959}, {"text": "de plus en plus chaud on a m\u00eame atteint", "start": 154.12, "duration": 4.08}, {"text": "les 80\u00b0gr au soleil dans le d\u00e9sert de", "start": 155.959, "duration": 4.64}, {"text": "Sonora en Am\u00e9rique alors cet \u00e9t\u00e9", "start": 158.2, "duration": 3.959}, {"text": "prot\u00e8ge-toi pour \u00e9viter les coups de", "start": 160.599, "duration": 3.601}, {"text": "soleil de l\u00e9g\u00e8res br\u00fblures provoqu\u00e9 par", "start": 162.159, "duration": 5.241}, {"text": "ces rayons", "start": 164.2, "duration": 3.2}]}